callipy.py
setup.py
callipy.egg-info/PKG-INFO
callipy.egg-info/SOURCES.txt
callipy.egg-info/dependency_links.txt
callipy.egg-info/requires.txt
callipy.egg-info/top_level.txt