Metadata-Version: 1.1
Name: callipy
Version: 0.3
Summary: Calling IPython notebooks with arguments
Home-page: UNKNOWN
Author: Damien Drix
Author-email: damien.drix+pypi@gmail.com
License: UNKNOWN
Platform: UNKNOWN
Classifier: Development Status :: 3 - Alpha
Classifier: Framework :: IPython
